<?xml version="1.0" encoding="UTF-8" ?>
<script name="stcw.convertCOMServiceTypeToGraniteOne">
  <label>Convert COM ServiceType To Granite One</label>
  <metaVersion>25</metaVersion>
  <parameterList>
    <parameter name="comServiceType" type="rifp">
      <type>dtype_stcw.string25</type>
    </parameter>
  </parameterList>
  <script><![CDATA[
    var result = null;

    if(stcc.stringHasValue(comServiceType)) {
        var convertValueFinder = new Finder ("stcconf.mapCOMToGraniteServiceTypeFinder");
        convertValueFinder.searchDocument.serviceType = comServiceType;
        convertValueFinder.search();

        var resultList = convertValueFinder.list;

        if (resultList != null && resultList.size > 0) {
            result = resultList.start.giServiceType;
        }
    }

    return result;
  ]]></script>
</script>