<?xml version="1.0" encoding="UTF-8" ?>
<dataStructure name="ifEAI_OCUA_17122008.OrderAcknowledgementRequest">
  <container>true</container>
  <label>OrderAcknowledgementRequest</label>
  <metaVersion>21</metaVersion>
  <xmlMap type="xmap">
    <includeXsiType>true</includeXsiType>
  </xmlMap>
  <childList>
    <child name="header" type="dstruct">
      <element>dstruct_ifEAI_OCUA_17122008.RequestHeader</element>
      <label>header</label>
      <mandatory>true</mandatory>
    </child>
    <child name="body" type="dstruct">
      <element>dstruct_ifEAI_OCUA_17122008.body</element>
      <label>body</label>
      <mandatory>true</mandatory>
    </child>
  </childList>
  <UserInterface name="UserInterface" type="tree">
    <defaultFolderImage>undefined</defaultFolderImage>
    <defaultLeafImage>undefined</defaultLeafImage>
    <element>dstruct_ifEAI_OCUA_17122008.OrderAcknowledgementRequest</element>
    <extends>tree_com.conceptwave.system.DataStructureUserInterface</extends>
    <tableDoc>doc_com.conceptwave.system.TreeDocument</tableDoc>
    <variableList>
      <variable name="model" type="uivar">
        <label>model</label>
        <valueType>dstruct_ifEAI_OCUA_17122008.OrderAcknowledgementRequest</valueType>
      </variable>
    </variableList>
    <vformList>
      <vform name="Forms" type="frmui">
        <extends>tree_com.conceptwave.system.DataStructureUserInterface/frmui_Forms</extends>
      </vform>
    </vformList>
  </UserInterface>
</dataStructure>