<?xml version="1.0" encoding="UTF-8" ?>
<dataType filenameHash="21c7b4341f6cf7c9e58b6f9b7c65eb1e" versionHash="a87ff679a2f3e71d9181a67b7542122c" name="ds_ws.provisioningFlag">
  <enumeration type="enum">
    <valueList>
      <value name="PROVISIONING" type="enumItem" code="PROVISIONING"/>
      <value name="ACTIVE" type="enumItem" code="ACTIVE"/>
      <value name="OLD" type="enumItem" code="OLD"/>
      <value name="CANCELLED" type="enumItem" code="CANCELLED"/>
    </valueList>
  </enumeration>
  <extends>dtype_com.conceptwave.system.String</extends>
  <label>Provisioning Flag</label>
  <length>12</length>
  <metaVersion>4</metaVersion>
</dataType>