<?xml version="1.0" encoding="UTF-8" ?>
<dataStructure filenameHash="1d796fda0263cbab5de0671a8a38db52" versionHash="eccbc87e4b5ce2fe28308fd9f2a7baf3" name="ifEAI_SIU_17122008.ArrayOfstring">
  <container>true</container>
  <guid>{0a1133eb-cb8e-cf0b-de96-0099f3c14a90}</guid>
  <label>ArrayOfstring</label>
  <metaVersion>3</metaVersion>
  <childList>
    <child name="ArrayOfstringItem" type="dstruct">
      <array>true</array>
      <datatype>true</datatype>
      <element>dtype_com.conceptwave.system.String</element>
      <guid>{04e34fda-6d27-19de-79e6-896033c934ab}</guid>
      <label>ArrayOfstringItem</label>
      <mandatory>true</mandatory>
      <maxInstance>-1</maxInstance>
      <minInstance>1</minInstance>
    </child>
  </childList>
  <UserInterface name="UserInterface" type="tree">
    <defaultFolderImage>undefined</defaultFolderImage>
    <defaultLeafImage>undefined</defaultLeafImage>
    <element>dstruct_ifEAI_SIU_17122008.ArrayOfstring</element>
    <extends>tree_com.conceptwave.system.DataStructureUserInterface</extends>
    <tableDoc>doc_com.conceptwave.system.TreeDocument</tableDoc>
    <variableList>
      <variable name="model" type="uivar">
        <label>model</label>
        <valueType>dstruct_ifEAI_SIU_17122008.ArrayOfstring</valueType>
      </variable>
    </variableList>
    <vformList>
      <vform name="Forms" type="frmui">
        <extends>tree_com.conceptwave.system.DataStructureUserInterface/frmui_Forms</extends>
      </vform>
    </vformList>
  </UserInterface>
</dataStructure>