<?xml version="1.0" encoding="UTF-8" ?>
<externalService filenameHash="7cd6b86e39eeaf545b966aa7d1072d20" versionHash="eccbc87e4b5ce2fe28308fd9f2a7baf3" name="grws.XngQuoteService_Service">
  <guid>{02713f69-2b45-02cc-dd65-fd782ced6ff5}</guid>
  <label>XngQuoteService_Service</label>
  <metaVersion>3</metaVersion>
  <portList>
    <port name="XngQuoteServiceSoapPort" type="port">
      <binding>bind_grws.XngQuoteServiceSoapBinding</binding>
      <label>XngQuoteServiceSoapPort</label>
      <logMessage>true</logMessage>
      <recover>5</recover>
    </port>
  </portList>
</externalService>