<?xml version="1.0" encoding="UTF-8" ?>
<document filenameHash="63eda01d06afe2210110bea85c71d076" versionHash="a87ff679a2f3e71d9181a67b7542122c" name="granite.searchUDAValue">
  <extends>doc_com.conceptwave.system.Document</extends>
  <guid>{42103130-b6fb-4678-938c-64de52ef2fbc}</guid>
  <label>Search Element: UDA Name</label>
  <metaVersion>4</metaVersion>
  <variableList>
    <variable name="ELEMENT_NAME" type="leaf">
      <valueType>dtype_granite.WO_NAME</valueType>
    </variable>
    <variable name="UDA_NAME" type="leaf">
      <valueType>dtype_com.conceptwave.system.String</valueType>
    </variable>
    <variable name="UDA_GROUP_NAME" type="leaf">
      <valueType>dtype_com.conceptwave.system.String</valueType>
    </variable>
  </variableList>
  <UserInterface name="UserInterface" type="ui">
    <extends>doc_com.conceptwave.system.Document/ui_UserInterface</extends>
    <variableList>
      <variable name="model" type="uivar">
        <label>model</label>
        <valueType>doc_granite.searchUDAValue</valueType>
      </variable>
    </variableList>
    <vformList>
      <vform name="Forms" type="frmui">
        <extends>doc_com.conceptwave.system.Document/ui_UserInterface/frmui_Forms</extends>
      </vform>
    </vformList>
  </UserInterface>
</document>